fairgraph/__init__.py
fairgraph/base.py
fairgraph/caching.py
fairgraph/client.py
fairgraph/collection.py
fairgraph/embedded.py
fairgraph/errors.py
fairgraph/fields.py
fairgraph/kgobject.py
fairgraph/kgproxy.py
fairgraph/kgquery.py
fairgraph/node.py
fairgraph/queries.py
fairgraph/registry.py
fairgraph/utility.py
fairgraph/openminds/__init__.py
fairgraph/openminds/controlledterms.py
fairgraph/openminds/specimenprep.py
fairgraph/openminds/chemicals/__init__.py
fairgraph/openminds/chemicals/amount_of_chemical.py
fairgraph/openminds/chemicals/chemical_mixture.py
fairgraph/openminds/chemicals/chemical_substance.py
fairgraph/openminds/chemicals/product_source.py
fairgraph/openminds/computation/__init__.py
fairgraph/openminds/computation/data_analysis.py
fairgraph/openminds/computation/data_copy.py
fairgraph/openminds/computation/environment.py
fairgraph/openminds/computation/generic_computation.py
fairgraph/openminds/computation/hardware_system.py
fairgraph/openminds/computation/launch_configuration.py
fairgraph/openminds/computation/local_file.py
fairgraph/openminds/computation/model_validation.py
fairgraph/openminds/computation/optimization.py
fairgraph/openminds/computation/simulation.py
fairgraph/openminds/computation/software_agent.py
fairgraph/openminds/computation/validation_test.py
fairgraph/openminds/computation/validation_test_version.py
fairgraph/openminds/computation/visualization.py
fairgraph/openminds/computation/workflow_execution.py
fairgraph/openminds/computation/workflow_recipe.py
fairgraph/openminds/computation/workflow_recipe_version.py
fairgraph/openminds/controlled_terms/__init__.py
fairgraph/openminds/controlled_terms/action_status_type.py
fairgraph/openminds/controlled_terms/age_category.py
fairgraph/openminds/controlled_terms/analysis_technique.py
fairgraph/openminds/controlled_terms/anatomical_axes_orientation.py
fairgraph/openminds/controlled_terms/anatomical_identification_type.py
fairgraph/openminds/controlled_terms/anatomical_plane.py
fairgraph-0.13.2.dist-info/licenses/LICENSE.txt
fairgraph-0.13.2.dist-info/METADATA
fairgraph-0.13.2.dist-info/WHEEL
fairgraph-0.13.2.dist-info/top_level.txt
fairgraph-0.13.2.dist-info/RECORD
