Metadata-Version: 2.4
Name: fairgraph
Version: 0.13.2
Summary: Python API for the EBRAINS Knowledge Graph
Author-email: "Andrew P. Davison" <andrew.davison@cnrs.fr>
License-Expression: Apache-2.0
Project-URL: Homepage, https://github.com/HumanBrainProject/fairgraph
Keywords: ebrains,hbp,metadata,electrophysiology,knowledge-graph
Classifier: Development Status :: 4 - Beta
Classifier: Intended Audience :: Science/Research
Classifier: Topic :: Scientific/Engineering
Classifier: Programming Language :: Python :: 3
Requires-Python: >=3.9
License-File: LICENSE.txt
Requires-Dist: ebrains-kg-core
Requires-Dist: openminds>=0.4.0
Requires-Dist: python-dateutil
Requires-Dist: tabulate
Requires-Dist: requests
Provides-Extra: dev
Requires-Dist: pytest; extra == "dev"
Requires-Dist: pytest-cov; extra == "dev"
Requires-Dist: pytest-mock; extra == "dev"
Requires-Dist: coverage; extra == "dev"
Requires-Dist: build; extra == "dev"
Requires-Dist: setuptools; extra == "dev"
Requires-Dist: wheel; extra == "dev"
Requires-Dist: sphinx; extra == "dev"
Requires-Dist: sphinxawesome_theme; extra == "dev"
Requires-Dist: black; extra == "dev"
Requires-Dist: twine; extra == "dev"
Provides-Extra: docs
Requires-Dist: sphinx; extra == "docs"
Requires-Dist: sphinxawesome_theme; extra == "docs"
Dynamic: license-file
